{
  "rapport_compression": {
    "image_originale": {
      "nom_image": "tmppaojvj3t.png",
      "resolution": "700x900",
      "taille_ko": 656.29,
      "type_detecte": "screenshot",
      "format_original": "PNG",
      "entropie": 3.2127,
      "densite_contours": 145495,
      "contient_texte": false
    },
    "decision_ia": {
      "format_choisi": "WEBP",
      "qualite_choisie": "0.75",
      "justification": "Le format WebP supporte la qualité dynamique, nous pouvons ainsi ajuster la qualité pour maximiser la compression tout en conservant la qualité visuelle.",
      "source": "—",
      "decision_pertinente": true,
      "niveau_pertinence": "Élevée"
    },
    "metriques_qualite": {
      "1_psnr_db": 22.41,
      "2_ssim": 0.9102,
      "3_mse": 373.2585,
      "4_taux_compression_pct": 96.04,
      "5_ratio_qualite_taille": 0.9303,
      "evaluation_qualite_visuelle": "Bon",
      "evaluation_efficacite_compression": "Excellent",
      "interpretation": {
        "psnr": "Qualité moyenne",
        "ssim": "Légère dégradation",
        "mse": "Erreur élevée",
        "gain": "Excellent (>50%)"
      }
    },
    "compression_appliquee": {
      "taille_originale_ko": 673.0,
      "taille_compressee_ko": 26.64,
      "ratio_compression": 25.26,
      "gain_pourcentage": 96.04,
      "format_utilise": "WEBP",
      "qualite_utilisee": 0,
      "qualite_ajustee": false,
      "nb_retries": 0
    },
    "analyse_categorie": {
      "type": "screenshot",
      "recommandation_theorique": "PNG ou WebP sans perte (conserve les détails)",
      "recommandation_appliquee": "WEBP q=0.75",
      "pertinence": "Élevée",
      "respecte_recommandation": true
    },
    "fichiers_generes": {
      "metrics_chart": "C:\\Users\\Lenovo ThinkPad T470\\OneDrive\\Documents\\Bureau\\Projet_Compression\\rapports\\tmppaojvj3t_20260328_224243\\metrics_chart.png",
      "compressed_image": "C:\\Users\\Lenovo ThinkPad T470\\OneDrive\\Documents\\Bureau\\Projet_Compression\\rapports\\tmppaojvj3t_20260328_224243\\tmppaojvj3t_compressed.webp"
    },
    "conclusion": "Qualité visuelle : Bon (SSIM=0.9102, PSNR=22.41 dB, MSE=373.26). Efficacité compression : Excellent — 96.0% économisé. Décision IA élevée — ✓ pertinente.",
    "date_analyse": "2026-03-28 22:42:46"
  }
}